README.md
setup.py
mttk/__init__.py
mttk.egg-info/PKG-INFO
mttk.egg-info/SOURCES.txt
mttk.egg-info/dependency_links.txt
mttk.egg-info/not-zip-safe
mttk.egg-info/requires.txt
mttk.egg-info/top_level.txt